apartments/__init__.py
apartments/url/__init__.py
apartments/url/base.py
apartments/url/keywords.py
apartments-0.0.1.dist-info/LICENSE
apartments-0.0.1.dist-info/WHEEL
apartments-0.0.1.dist-info/METADATA
apartments-0.0.1.dist-info/RECORD
